tests/__init__.py
tests/test_base.py
tests/test_envs.py
tests/test_tpu_info.py
tests/test_utils.py
tests/core/__init__.py
tests/core/test_core_tpu.py
tests/core/test_disagg_executor.py
tests/core/test_disagg_utils.py
tests/core/test_dp_scheduler.py
tests/core/test_init.py
tests/distributed/__init__.py
tests/distributed/test_distributed_utils.py
tests/distributed/test_tpu_connector.py
tests/e2e/__init__.py
tests/e2e/test_async_scheduler.py
tests/e2e/test_data_parallel.py
tests/e2e/test_hybrid_kvcache.py
tests/e2e/test_local_disagg.py
tests/e2e/test_model_loader.py
tests/e2e/test_multi_modal_inference.py
tests/e2e/test_pipeline_parallel.py
tests/e2e/test_runai_model_streamer_loader.py
tests/e2e/test_sampling_params.py
tests/e2e/test_speculative_decoding.py
tests/e2e/test_structured_decoding.py
tests/executors/__init__.py
tests/executors/test_ray_distributed_executor.py
tests/experimental/__init__.py
tests/experimental/test_llama3_jax_stashed.py
tests/kernels/__init__.py
tests/kernels/fused_moe_v1_test.py
tests/kernels/gmm_test.py
tests/kernels/mla_v1_test.py
tests/kernels/quantized_matmul_kernel_test.py
tests/kernels/ragged_kv_cache_update_v2_test.py
tests/kernels/ragged_paged_attention_kernel_v2_test.py
tests/kernels/ragged_paged_attention_kernel_v3_hd64_test.py
tests/kernels/ragged_paged_attention_kernel_v3_test.py
tests/kernels/collectives/__init__.py
tests/kernels/collectives/all_gather_matmul_kernel_test.py
tests/layers/__init__.py
tests/layers/common/__init__.py
tests/layers/common/test_attention_interface.py
tests/layers/common/test_quantization.py
tests/layers/jax/__init__.py
tests/layers/jax/test_layers.py
tests/layers/jax/test_qwix.py
tests/layers/jax/test_rope.py
tests/layers/jax/test_sharding.py
tests/layers/jax/test_transformer_block.py
tests/layers/jax/attention/__init__.py
tests/layers/jax/attention/test_common_attention.py
tests/layers/jax/attention/test_deepseek_v3_attention.py
tests/layers/jax/attention/test_llama4_attention.py
tpu_inference-0.13.3.dist-info/licenses/LICENSE
tpu_inference-0.13.3.dist-info/METADATA
tpu_inference-0.13.3.dist-info/WHEEL
tpu_inference-0.13.3.dist-info/top_level.txt
tpu_inference-0.13.3.dist-info/RECORD
