Metadata-Version: 2.4
Name: tpu_inference
Version: 0.13.3
Author: tpu_inference Contributors
Classifier: Development Status :: 3 - Alpha
Classifier: Intended Audience :: Developers
Classifier: Intended Audience :: Education
Classifier: Intended Audience :: Science/Research
Classifier: License :: OSI Approved :: Apache Software License
Classifier: Programming Language :: Python :: 3.10
Classifier: Programming Language :: Python :: 3.11
Classifier: Programming Language :: Python :: 3.12
Classifier: Topic :: Scientific/Engineering :: Artificial Intelligence
Requires-Python: >=3.10
License-File: LICENSE
Requires-Dist: tpu-info==0.7.1
Requires-Dist: yapf==0.43.0
Requires-Dist: pytest
Requires-Dist: pytest-mock
Requires-Dist: absl-py
Requires-Dist: numpy
Requires-Dist: google-cloud-storage
Requires-Dist: jax==0.8.1
Requires-Dist: jaxlib==0.8.1
Requires-Dist: jaxtyping==0.3.2
Requires-Dist: flax==0.11.1
Requires-Dist: torchax==0.0.10
Requires-Dist: qwix==0.1.1
Requires-Dist: torchvision==0.24.0
Requires-Dist: pathwaysutils
Requires-Dist: parameterized
Requires-Dist: numba==0.62.1
Requires-Dist: runai-model-streamer[gcs,s3]==0.15.0
Requires-Dist: libtpu==0.0.31
Dynamic: author
Dynamic: classifier
Dynamic: description
Dynamic: description-content-type
Dynamic: license-file
Dynamic: requires-dist
Dynamic: requires-python
